napalm_ros/__init__.py
napalm_ros/query.py
napalm_ros/ros.py
napalm_ros/utils.py
napalm_ros-1.2.6.dist-info/METADATA
napalm_ros-1.2.6.dist-info/WHEEL
napalm_ros-1.2.6.dist-info/RECORD
