Metadata-Version: 2.1
Name: napalm-ros
Version: 1.2.6
Summary: Network Automation and Programmability Abstraction Layer driver for Mikrotik ROS
Home-page: https://github.com/napalm-automation-community/napalm-ros/issues
License: GPL-2.0-or-later
Keywords: mikrotik,routeros,api,napalm
Author: Łukasz Kostka
Author-email: lukasz.g.kostka@gmail.com
Requires-Python: >=3.7.2,<4.0.0
Classifier: License :: OSI Approved :: GNU General Public License v2 or later (GPLv2+)
Classifier: Programming Language :: Python :: 3
Classifier: Programming Language :: Python :: 3.8
Classifier: Programming Language :: Python :: 3.9
Classifier: Programming Language :: Python :: 3.10
Classifier: Programming Language :: Python :: 3.11
Requires-Dist: librouteros (>=3.2.0,<4.0.0)
Requires-Dist: napalm (>=4.0.0,<5.0.0)
Project-URL: Documentation, https://github.com/napalm-automation-community/napalm-ros
Project-URL: Repository, https://github.com/napalm-automation-community/napalm-ros/issues
